{
  "type": "minecraft:block",
  "pools": [
    {
      "name": "fluid_absorber",
      "rolls": 1.0,
      "bonus_rolls": 0.0,
      "entries": [
        {
          "type": "minecraft:item",
          "functions": [
            {
              "function": "minecraft:copy_name",
              "source": "block_entity"
            },
            {
              "function": "minecraft:copy_nbt",
              "source": "block_entity",
              "ops": [
                {
                  "source": "Info",
                  "target": "BlockEntityTag.Info",
                  "op": "replace"
                },
                {
                  "source": "Items",
                  "target": "BlockEntityTag.Items",
                  "op": "replace"
                },
                {
                  "source": "Energy",
                  "target": "BlockEntityTag.Energy",
                  "op": "replace"
                }
              ]
            },
            {
              "function": "minecraft:set_contents",
              "type": "rftoolsdim:fluid_absorber",
              "entries": [
                {
                  "type": "minecraft:dynamic",
                  "name": "minecraft:contents"
                }
              ]
            }
          ],
          "name": "rftoolsdim:fluid_absorber"
        }
      ]
    }
  ]
}